vipdopt/GDS.py
vipdopt/STL.py
vipdopt/__init__.py
vipdopt/__main__ v1.py
vipdopt/__main__.py
vipdopt/__main__v0.py
vipdopt/lumerical.cfg
vipdopt/project.py
vipdopt/submit.sh
vipdopt/submit_job.py
vipdopt/utils.py
vipdopt-2.0.2.dist-info/LICENSE.md
vipdopt-2.0.2.dist-info/LICENSE.txt
vipdopt-2.0.2.dist-info/METADATA
vipdopt-2.0.2.dist-info/WHEEL
vipdopt-2.0.2.dist-info/top_level.txt
vipdopt-2.0.2.dist-info/RECORD
