Metadata-Version: 2.1
Name: vipdopt
Version: 2.0.2
Summary: Package for volumetirc inverse photonic design and optimization
Author-email: "McNichols, N.; Foo, I.; Roberts, G." <ianfoo@caltech.edu>
Maintainer-email: Ian Foo <ianfoo@caltech.edu>
Project-URL: Homepage, https://github.com/IanFooMZ/SonyBayerFilter
Project-URL: Issues, https://github.com/IanFooMZ/SonyBayerFilter/issues
Classifier: Programming Language :: Python :: 3
Requires-Python: ==3.10.*
License-File: LICENSE.md
License-File: LICENSE.txt
Requires-Dist: scipy ==1.12.*
Requires-Dist: numpy ==1.26.*
Requires-Dist: numpy-stl ==3.1.*
Requires-Dist: matplotlib ==3.8.*
Requires-Dist: scikit-image ==0.22.*
Requires-Dist: overrides ==7.7.*
Requires-Dist: PyYAML ==6.*
Requires-Dist: types-PyYAML ==6.*
Requires-Dist: python-magic ==0.4.*
Requires-Dist: Jinja2 ==3.1.*
Requires-Dist: PySide6 ==6.3.0
Requires-Dist: PySide6-stubs ==6.4.2
Requires-Dist: gdstk ==0.9.50
Requires-Dist: python-magic-bin ; platform_system == "Windows"
Provides-Extra: dev
Requires-Dist: sphinx ==7.3.7 ; extra == 'dev'
Requires-Dist: nbsphinx ==0.9.4 ; extra == 'dev'
Requires-Dist: furo ==2024.5.6 ; extra == 'dev'
Requires-Dist: notebook ==7.2.1 ; extra == 'dev'
Requires-Dist: sphinx-gallery ==0.17.0 ; extra == 'dev'
Requires-Dist: sphinx-tabs ==3.4.5 ; extra == 'dev'
Requires-Dist: pypandoc ==1.13 ; extra == 'dev'
Requires-Dist: pytest ==8.* ; extra == 'dev'
Requires-Dist: pytest-cov ==4.1.* ; extra == 'dev'
Requires-Dist: pytest-xdist ==3.5.* ; extra == 'dev'
Requires-Dist: pytest-mock ==3.12.* ; extra == 'dev'
Requires-Dist: mypy ==1.8.* ; extra == 'dev'
Requires-Dist: coverage[toml] ==7.4.3 ; extra == 'dev'
Requires-Dist: ruff ==0.3.5 ; extra == 'dev'
Requires-Dist: jax ==0.4.30 ; extra == 'dev'
Requires-Dist: jaxlib ==0.4.30 ; extra == 'dev'
